{
  "version": 1,
  "locales": ["fr"],
  "nodes": [
    {
      "id": "intro_baobab_maminiaina",
      "speaker": "Dadatoa Maminiaina",
      "lines": [
        "Hitanao io hazo io, anaka? Efa 300 taona izy. Nilalao teo ambanin'ny rantsany ny raiben-draibenao. Manan-jo handrava azy ve ianao?"
      ],
      "choices": [
        {
          "text": "Tsia. Fa ahoana no hampahafantarako izany amin'ireo noana?",
          "effects": { "fihavanana": 5, "unlock": "power_forest_listen" },
          "next": "intro_baobab_maminiaina_end"
        }
      ]
    },
    {
      "id": "intro_baobab_maminiaina_end",
      "speaker": "Dadatoa Maminiaina",
      "lines": [
        "Izay no fanontaniana marina, Ravo. Ary izay no antony maha-eto anao. Tsy hiady no nahatongavanao fa hihaino. Miteny ny ala. Ianaro ny fiteniny."
      ],
      "choices": []
    }
  ]
}
